{"id":"index.html","dependencies":[{"name":"/Users/jchu4483/Desktop/Node/pet-finder/package.json","includedInParent":true,"mtime":1532290383973},{"name":"./stylesheets/styles.css","dynamic":true,"parent":"/Users/jchu4483/Desktop/Node/pet-finder/index.html","resolved":"/Users/jchu4483/Desktop/Node/pet-finder/stylesheets/styles.css"},{"name":"./js/main.js","dynamic":true,"parent":"/Users/jchu4483/Desktop/Node/pet-finder/index.html","resolved":"/Users/jchu4483/Desktop/Node/pet-finder/js/main.js"}],"generated":{"html":"<!DOCTYPE html>\n<html lang=\"en\">\n<head>\n  <meta charset=\"UTF-8\">\n  <meta name=\"viewport\" content=\"width=device-width, initial-scale=1.0\">\n  <meta http-equiv=\"X-UA-Compatible\" content=\"ie=edge\">\n  <link rel=\"stylesheet\" href=\"/ca3f091bcb0d8ce3b2b9b7bf80355cbf.css\">\n  <title>Document</title>\n</head>\n<body></body>\n\n    <div class=\"container\">\n      <form id=\"petForm\">\n        <span class=\"petName\">Animal</span>\n        <select id=\"petName\" name=\"petName\"> \n          <option value=\"dog\">Dog</option>\n          <option value=\"cat\">Cat</option>\n        </select>\n          Zipcode:\n        <input id=\"zipcode\" type=\"text\" name=\"zipcode\">\n        <input type=\"submit\" value=\"Find\">\n      </form>\n    </div>\n\n    <div class=\"pet-display-container\">\n      <ul id=\"petsListings\">\n\n      </ul>\n    </div>\n\n    <script src=\"/d451766c1bbcf10862ee2a9adfd497d5.js\"></script>\n\n</html>"},"hash":"a288ea64e5deb650e2b9a52ecdf40369","cacheData":{}}